Workbook

Sheet Summary Dashboard
A1: HK Life Insurance Daily Product Briefing
A2: Report Date | B2: 2026-05-31 | C2: Generated | D2: 2026-05-31 08:00 HKT | E2: Research Window | F2: 2026-05-24 to 2026-05-31
A3: Total tracked product/product-related entries | B3: =COUNTA('All Products'!A2:A9) -> 8 | C3: Official top-10 items in strict 7-day window | D3: 1 | E3: New launches past 48h | F3: 0
A4: Product updates / active promotions | B4: 6 | C4: Source credibility | D4: Official insurer/regulatory sources prioritized; financial press used only for market context
A5: Market note | B5: Quiet week: no official top-10 Class A/C/D new product launch found in the past 48 hours; one China Life (Overseas) medical service update fell within the 7-day window.
A7: Count by Category | D7: Count by Insurer
A8: Savings | B8: =COUNTIF('All Products'!C2:C9,"Savings") -> 3 | D8: AIA International Limited | E8: 2
A9: QDAP | B9: =COUNTIF('All Products'!C2:C9,"QDAP") -> 0 | D9: China Life Insurance | E9: 1
A10: VHIS | B10: =COUNTIF('All Products'!C2:C9,"VHIS") -> 2 | D10: FWD Life Insurance Company | E10: 3
A11: Medical | B11: =COUNTIF('All Products'!C2:C9,"Medical") -> 2 | D11: Manulife (International) Limited | E11: 1
A12: Critical Illness | B12: =COUNTIF('All Products'!C2:C9,"Critical Illness") -> 1 | D12: Zurich Life Insurance | E12: 1
A14: Regulatory Intelligence
A15: VHIS | B15: VHIS FAQ states 100 Certified Plans and 573 products as of 2026-03-31.
A16: QDAP | B16: IA QDAP list checked; no top-10 new QDAP launch found in this run.
A17: IA / MPFA | B17: IA circulars and MPFA updates checked; no immediate pricing-product filing found in the past 7 days.

Sheet All Products
A1: Insurer | B1: Product Name | C1: Product Category | D1: IA Class | E1: Currency | F1: Issue Date / Announcement Date | G1: Source URL | H1: Premium Payment Terms | I1: Premium Range | J1: Issue Age | K1: Key Benefit Summary | L1: Update Type | M1: Recency Flag
A2: China Life Insurance (Overseas) Company Limited (中國人壽保險（海外）) | B2: Oncology direct-billing service expansion with New Frontier Health (腫瘤專科門診直付理賠服務) | C2: Medical | D2: Class D | E2: HKD | F2: 2026-05-26 | G2: =HYPERLINK("https://www.chinalife.com.hk/zh-hk/about-us/news-center/china-life-overseas-and-new-frontier-health-hong-kong-forge-strategic","Open source") -> Open source | H2: N/A - service/network enhancement for eligible personal medical insurance customers | I2: N/A | J2: N/A | K2: Strategic partnership extends China Life (Overseas)' medical direct-billing network from inpatient services into specialist oncology outpatient services, day treatment, drugs and imaging diagnosis via Hong Kong Integrated Oncology Centre and Icon Cancer Centre. | L2: Product-related service update | M2: Past 7 days
A3: FWD Life Insurance Company (Bermuda) Limited (富衛人壽保險) | B3: MyCover Critical Illness Plan | C3: Critical Illness | D3: Class D | E3: HKD | F3: N/A - active official online promotion as of 2026-05-31; offer ends 2026-06-10 | G3: =HYPERLINK("https://www.fwd.com.hk/online-insurance/term-critical-illness/en/","Open source") -> Open source | H3: Yearly renewable / 10-year renewable; premium payment to policy anniversary immediately preceding age 85 | I3: Monthly premium shown as low as HK$14.31; sum insured HK$300,000-HK$2,500,000 depending on age | J3: Age next birthday 1 (15 days) to 70 | K3: Online term CI plan covering the big three diseases, carcinoma-in-situ and early malignancies; optional Crisis Benefit adds 59 additional critical illnesses, and MyCover 2-in-1 adds post-claim medical reimbursement for the big three diseases. | L3: Current promotion / product page update | M3: Current offer
A4: FWD Life Insurance Company (Bermuda) Limited (富衛人壽保險) | B4: vPrime Medical Plan (VHIS Flexi Plan) | C4: VHIS | D4: Class D | E4: HKD | F4: N/A - active official online promotion as of 2026-05-31; offer ends 2026-06-10 | G4: =HYPERLINK("https://www.fwd.com.hk/online-insurance/vhis-vprime-medical-plan/en/","Open source") -> Open source | H4: Regular pay; online monthly/annual quote options shown | I4: Illustrative first-year monthly premium from HK$119-HK$917 for ANB31 depending on deductible, after promotion assumptions | J4: N/A in public page excerpt | K4: VHIS Flexi medical plan with annual benefit limit up to HK$12.5 million, no lifetime benefit limit, six deductible options, deductible waiver for designated crises, cash benefits and no-claims premium discount. | L4: Current promotion / product page update | M4: Current offer
A5: FWD Life Insurance Company (Bermuda) Limited (富衛人壽保險) | B5: One&All Medical Insurance Plan | C5: Medical | D5: Class D | E5: HKD | F5: 2025-08-17; current online promotion as of 2026-05-31 ends 2026-06-10 | G5: =HYPERLINK("https://www.fwd.com.hk/online-insurance/online-promotions/en/","Open source") -> Open source | H5: Regular pay | I5: Daily premium less than HK$3; current promotion shows total 12-month premium waiver in first 2 years | J5: N/A in public page excerpt | K5: Mass-market medical cover positioned around flexible public/private hospital-type segmentation and affordable entry protection; active online promotion offers premium waiver benefits. | L5: Current promotion | M5: Current offer
A6: AIA International Limited (友邦保險) | B6: ProsperLife Insurance Plan (活然人生保險計劃) | C6: Savings | D6: Class A | E6: HKD | F6: 2026-03-31; campaign issuance deadline 2026-05-31 | G6: =HYPERLINK("https://www.aia.com.hk/en/about-aia/about-us/media-centre/press-releases/2026/aia-press-release-20260331","Open source") -> Open source | H6: Regular pay; product launch example cites premiums from HKD60 per day | I6: Example: HKD60 per day for HKD1.9 million sum assured | J6: N/A in release | K6: Participating whole life plan focused on mortality protection and family settlement flexibility, with death benefit settlement options and first-in-market Beneficiary Flexi Option for beneficiary-driven payout timing after designated age or specified illness. | L6: Latest 2026 launch / active campaign deadline | M6: Older launch; current campaign
A7: Zurich Life Insurance (Hong Kong) Limited (蘇黎世人壽保險（香港）) | B7: Swiss Prime Savings Insurance Plan (瑞盈儲蓄保險計劃) | C7: Savings | D7: Class A | E7: Multi-currency / 7 settlement currencies | F7: 2026-03-10; policy issue deadline for launch offer 2026-05-29 | G7: =HYPERLINK("https://www.zurich.com.hk/en/about-zurich/news-and-announcements/2026/2026-0310","Open source") -> Open source | H7: 2-pay / 5-pay | I7: N/A in release; launch offer up to 58% first-year annualized premium discount plus prepayment interest offer | J7: N/A in release | K7: Participating savings plan with short premium commitment, guaranteed cash value, non-guaranteed terminal bonus, terminal bonus lock-in, premium holiday and estate/legacy options including policy split and contingent policyholder nomination. | L7: Latest 2026 launch / offer deadline | M7: Older launch; May offer deadline
A8: Manulife (International) Limited (宏利人壽保險) | B8: GoldenStart Whole Life Immediate Annuity Insurance Plan (宏瑞終身即期年金保險計劃) | C8: Savings | D8: Class A | E8: N/A in release | F8: 2026-04-20 | G8: =HYPERLINK("https://www.manulife.com.hk/en/individual/about/newsroom/manulife-launches-new-annuity-and-accident-protection-solutions.html","Open source") -> Open source | H8: Single premium | I8: N/A in release | J8: N/A in release | K8: Whole-life immediate annuity converting single premium into guaranteed monthly income for life, with non-guaranteed terminal bonus potential, Whole Care Benefit for 14 designated critical/mental illness conditions and By Your Side annual payments for Severe Dementia or Parkinson's Disease before age 80. | L8: Latest 2026 launch found | M8: Older launch
A9: AIA International Limited (友邦保險) | B9: AIA Voluntary Health Insurance SelectWise Scheme | C9: VHIS | D9: Class D | E9: HKD | F9: 2026-02-03 | G9: =HYPERLINK("https://www.aia.com.hk/en/about-aia/about-us/media-centre/press-releases/2026/aia-press-release-20260203","Open source") -> Open source | H9: Regular pay | I9: N/A in release | J9: N/A in release | K9: VHIS certified plan with no itemised benefit sublimits, designated hospital network, upgraded room options subject to pre-authorization and network doctor conditions, annual limit up to HK$12 million and lifetime limit up to HK$60 million. | L9: Latest 2026 launch found | M9: Older launch

Sheet Savings & QDAP
A1: Insurer | B1: Product Name | C1: Product Category | D1: IA Class | E1: Currency | F1: Issue Date / Announcement Date | G1: Source URL | H1: Premium Payment Terms | I1: Premium Range | J1: Issue Age | K1: Key Benefit Summary | L1: Update Type | M1: Recency Flag | N1: Guaranteed Cash Value / IRR | O1: Non-Guaranteed Projected Return | P1: Bonus / Dividend Structure | Q1: Premium Holiday / Flexibility | R1: Policy Loan | S1: QDAP Tax Deduction | T1: Annuity Commencement
A2: AIA International Limited (友邦保險) | B2: ProsperLife Insurance Plan (活然人生保險計劃) | C2: Savings | D2: Class A | E2: HKD | F2: 2026-03-31; campaign issuance deadline 2026-05-31 | G2: =HYPERLINK("https://www.aia.com.hk/en/about-aia/about-us/media-centre/press-releases/2026/aia-press-release-20260331","Open source") -> Open source | H2: Regular pay; product launch example cites premiums from HKD60 per day | I2: Example: HKD60 per day for HKD1.9 million sum assured | J2: N/A in release | K2: Participating whole life plan focused on mortality protection and family settlement flexibility, with death benefit settlement options and first-in-market Beneficiary Flexi Option for beneficiary-driven payout timing after designated age or specified illness. | L2: Latest 2026 launch / active campaign deadline | M2: Older launch; current campaign | N2: Guaranteed cash value not disclosed in release | O2: N/A | P2: Participating whole life; release does not disclose dividend mechanics | Q2: Death Benefit Settlement Option; Beneficiary Flexi Option; add-on riders; PRMP eligible | R2: N/A in release | S2: N/A | T2: N/A
A3: Zurich Life Insurance (Hong Kong) Limited (蘇黎世人壽保險（香港）) | B3: Swiss Prime Savings Insurance Plan (瑞盈儲蓄保險計劃) | C3: Savings | D3: Class A | E3: Multi-currency / 7 settlement currencies | F3: 2026-03-10; policy issue deadline for launch offer 2026-05-29 | G3: =HYPERLINK("https://www.zurich.com.hk/en/about-zurich/news-and-announcements/2026/2026-0310","Open source") -> Open source | H3: 2-pay / 5-pay | I3: N/A in release; launch offer up to 58% first-year annualized premium discount plus prepayment interest offer | J3: N/A in release | K3: Participating savings plan with short premium commitment, guaranteed cash value, non-guaranteed terminal bonus, terminal bonus lock-in, premium holiday and estate/legacy options including policy split and contingent policyholder nomination. | L3: Latest 2026 launch / offer deadline | M3: Older launch; May offer deadline | N3: Guaranteed cash value offers predictable returns and may increase over policy years; detailed IRR not disclosed in release | O3: Non-guaranteed terminal bonus; projected IRR not disclosed in release | P3: Non-guaranteed terminal bonus with lock-in option | Q3: Premium holiday, 7 settlement currencies, access to policy value, policy split, change of life insured/policyholder, contingent life insured and contingent policyholder nomination. | R3: Access to policy value disclosed; LTV not disclosed | S3: N/A | T3: N/A
A4: Manulife (International) Limited (宏利人壽保險) | B4: GoldenStart Whole Life Immediate Annuity Insurance Plan (宏瑞終身即期年金保險計劃) | C4: Savings | D4: Class A | E4: N/A in release | F4: 2026-04-20 | G4: =HYPERLINK("https://www.manulife.com.hk/en/individual/about/newsroom/manulife-launches-new-annuity-and-accident-protection-solutions.html","Open source") -> Open source | H4: Single premium | I4: N/A in release | J4: N/A in release | K4: Whole-life immediate annuity converting single premium into guaranteed monthly income for life, with non-guaranteed terminal bonus potential, Whole Care Benefit for 14 designated critical/mental illness conditions and By Your Side annual payments for Severe Dementia or Parkinson's Disease before age 80. | L4: Latest 2026 launch found | M4: Older launch | N4: Guaranteed monthly income for life commencing from first monthiversary | O4: Non-guaranteed terminal bonus may be payable on surrender, termination or death | P4: Non-guaranteed terminal bonus reviewed at least monthly | Q4: Whole Care Benefit can realize part of available terminal bonus after 14 specified critical/mental illnesses; By Your Side Benefit pays annual amounts for up to 10 years after Severe Dementia/Parkinson's diagnosis before age 80. | R4: N/A in release | S4: N/A - immediate annuity, not identified as QDAP | T4: First monthiversary

Sheet VHIS & Medical
A1: Insurer | B1: Product Name | C1: Product Category | D1: IA Class | E1: Currency | F1: Issue Date / Announcement Date | G1: Source URL | H1: Premium Payment Terms | I1: Premium Range | J1: Issue Age | K1: Key Benefit Summary | L1: Update Type | M1: Recency Flag | N1: Plan Type | O1: Room Class | P1: Annual Benefit Limit | Q1: Lifetime Benefit Limit | R1: Key Claimable Items | S1: Co-payment / Deductible | T1: Pre-existing Condition | U1: Cancer Coverage
A2: China Life Insurance (Overseas) Company Limited (中國人壽保險（海外）) | B2: Oncology direct-billing service expansion with New Frontier Health (腫瘤專科門診直付理賠服務) | C2: Medical | D2: Class D | E2: HKD | F2: 2026-05-26 | G2: =HYPERLINK("https://www.chinalife.com.hk/zh-hk/about-us/news-center/china-life-overseas-and-new-frontier-health-hong-kong-forge-strategic","Open source") -> Open source | H2: N/A - service/network enhancement for eligible personal medical insurance customers | I2: N/A | J2: N/A | K2: Strategic partnership extends China Life (Overseas)' medical direct-billing network from inpatient services into specialist oncology outpatient services, day treatment, drugs and imaging diagnosis via Hong Kong Integrated Oncology Centre and Icon Cancer Centre. | L2: Product-related service update | M2: Past 7 days | N2: Medical service/network enhancement for eligible personal medical insurance customers | O2: N/A | P2: N/A | Q2: N/A | R2: Oncology specialist outpatient, day treatment, drugs, imaging diagnosis and one-stop direct settlement support after pre-approval. | S2: N/A | T2: Subject to underlying medical policy terms; not disclosed in release. | U2: Cancer treatment pathway support through oncology centres and direct billing.
A3: FWD Life Insurance Company (Bermuda) Limited (富衛人壽保險) | B3: vPrime Medical Plan (VHIS Flexi Plan) | C3: VHIS | D3: Class D | E3: HKD | F3: N/A - active official online promotion as of 2026-05-31; offer ends 2026-06-10 | G3: =HYPERLINK("https://www.fwd.com.hk/online-insurance/vhis-vprime-medical-plan/en/","Open source") -> Open source | H3: Regular pay; online monthly/annual quote options shown | I3: Illustrative first-year monthly premium from HK$119-HK$917 for ANB31 depending on deductible, after promotion assumptions | J3: N/A in public page excerpt | K3: VHIS Flexi medical plan with annual benefit limit up to HK$12.5 million, no lifetime benefit limit, six deductible options, deductible waiver for designated crises, cash benefits and no-claims premium discount. | L3: Current promotion / product page update | M3: Current offer | N3: VHIS Flexi | O3: N/A in page excerpt | P3: Up to HK$12.5 million per policy year | Q3: No lifetime benefit limit | R3: Hospitalisation and surgical expenses, eligible medical expenses, cash benefits, day case procedures, ICU, major/complex surgeries. | S3: Deductible options HK$0 / 16,000 / 25,000 / 50,000 / 100,000 / 250,000 | T3: Public page states unknown pre-existing conditions, including congenital conditions, are covered subject to terms. | U3: Deductible waiver for designated crises, example includes stage 3 breast cancer.
A4: FWD Life Insurance Company (Bermuda) Limited (富衛人壽保險) | B4: One&All Medical Insurance Plan | C4: Medical | D4: Class D | E4: HKD | F4: 2025-08-17; current online promotion as of 2026-05-31 ends 2026-06-10 | G4: =HYPERLINK("https://www.fwd.com.hk/online-insurance/online-promotions/en/","Open source") -> Open source | H4: Regular pay | I4: Daily premium less than HK$3; current promotion shows total 12-month premium waiver in first 2 years | J4: N/A in public page excerpt | K4: Mass-market medical cover positioned around flexible public/private hospital-type segmentation and affordable entry protection; active online promotion offers premium waiver benefits. | L4: Current promotion | M4: Current offer | N4: Medical insurance | O4: Segmented by hospital type / benefit level | P4: N/A in current promotion page | Q4: N/A in current promotion page | R4: Self-financed public hospital items, drugs, imaging tests and selected private medical support as described by FWD launch materials. | S4: N/A | T4: N/A | U4: N/A in current promotion page
A5: AIA International Limited (友邦保險) | B5: AIA Voluntary Health Insurance SelectWise Scheme | C5: VHIS | D5: Class D | E5: HKD | F5: 2026-02-03 | G5: =HYPERLINK("https://www.aia.com.hk/en/about-aia/about-us/media-centre/press-releases/2026/aia-press-release-20260203","Open source") -> Open source | H5: Regular pay | I5: N/A in release | J5: N/A in release | K5: VHIS certified plan with no itemised benefit sublimits, designated hospital network, upgraded room options subject to pre-authorization and network doctor conditions, annual limit up to HK$12 million and lifetime limit up to HK$60 million. | L5: Latest 2026 launch found | M5: Older launch | N5: VHIS Flexi certified plan | O5: Basic ward across Asia; semi-private at eligible designated hospitals in Hong Kong/Macau; Mainland designated hospital room options. | P5: Up to HK$12 million | Q5: Up to HK$60 million | R5: Hospitalisation, surgical, pre/post confinement, day case outpatient, Chinese medicine outpatient, day surgery cash benefits and Care Concierge services. | S5: Annual deductible options; elderly designated-cancer deductible waiver disclosed | T5: Subject to VHIS policy terms; release highlights certified VHIS status | U5: Deductible waiver for designated cancer if insured age 75+ and conditions met; designated cancer includes malignant cancer and carcinoma-in-situ with exclusions.

Sheet Critical Illness
A1: Insurer | B1: Product Name | C1: Product Category | D1: IA Class | E1: Currency | F1: Issue Date / Announcement Date | G1: Source URL | H1: Premium Payment Terms | I1: Premium Range | J1: Issue Age | K1: Key Benefit Summary | L1: Update Type | M1: Recency Flag | N1: Number of Covered Conditions | O1: Severity Structure | P1: Multi-pay Structure | Q1: Sum Assured Range | R1: Premium Waiver | S1: Cancer Definition | T1: Mental Health / Diabetes Coverage
A2: FWD Life Insurance Company (Bermuda) Limited (富衛人壽保險) | B2: MyCover Critical Illness Plan | C2: Critical Illness | D2: Class D | E2: HKD | F2: N/A - active official online promotion as of 2026-05-31; offer ends 2026-06-10 | G2: =HYPERLINK("https://www.fwd.com.hk/online-insurance/term-critical-illness/en/","Open source") -> Open source | H2: Yearly renewable / 10-year renewable; premium payment to policy anniversary immediately preceding age 85 | I2: Monthly premium shown as low as HK$14.31; sum insured HK$300,000-HK$2,500,000 depending on age | J2: Age next birthday 1 (15 days) to 70 | K2: Online term CI plan covering the big three diseases, carcinoma-in-situ and early malignancies; optional Crisis Benefit adds 59 additional critical illnesses, and MyCover 2-in-1 adds post-claim medical reimbursement for the big three diseases. | L2: Current promotion / product page update | M2: Current offer | N2: Big 3 diseases; carcinoma-in-situ / early-stage malignancies; optional additional 59 critical illnesses | O2: Multi-tier: early carcinoma-in-situ / early malignancy plus major CI lump sum | P2: Single major CI structure; MyCover 2-in-1 adds two-year medical reimbursement after big-three claim | Q2: HK$300,000-HK$2,500,000 for ANB 1-60; HK$300,000-HK$1,500,000 for ANB 61-70 | R2: N/A in public page | S2: Covers carcinoma-in-situ of specified organs and early-stage malignancy of prostate, thyroid and non-melanoma skin cancer; pays 35% of initial sum insured up to HK$400,000. | T2: N/A in public page

Sheet Sources Log
A1: Source Type | B1: Query / URL | C1: Date-Time Accessed | D1: Content Found | E1: Notes
A2: Search query | B2: Hong Kong life insurance new product launch 2026 | C2: 2026-05-31 08:00 HKT | D2: Yes | E2: Specified English query; found AIA ProsperLife and other market results.
A3: Search query | B3: AIA Manulife Prudential FWD Sun Life HSBC BOC Life new product Hong Kong 2026 | C3: 2026-05-31 08:00 HKT | D3: Yes | E3: Specified English query; found current/older launches and official pages.
A4: Search query | B4: QDAP Hong Kong new 2026 | C4: 2026-05-31 08:00 HKT | D4: Limited | E4: Specified English query; IA QDAP list found, no new top-10 QDAP launch in past 7 days.
A5: Search query | B5: VHIS new plan Hong Kong 2026 | C5: 2026-05-31 08:00 HKT | D5: Yes | E5: Specified English query; VHIS official list and AIA/FWD VHIS product pages found.
A6: Search query | B6: critical illness insurance Hong Kong new launch 2026 | C6: 2026-05-31 08:00 HKT | D6: Yes | E6: Specified English query; found FWD MyCover and non-target insurer CI launches.
A7: Search query | B7: savings insurance Hong Kong new 2026 | C7: 2026-05-31 08:00 HKT | D7: Yes | E7: Specified English query; found AIA, Zurich and other savings products.
A8: Search query | B8: site:aia.com.hk OR site:manulife.com.hk OR site:prudential.com.hk new product 2026 | C8: 2026-05-31 08:00 HKT | D8: Yes | E8: Specified English query; official AIA/Manulife results found.
A9: Search query | B9: 香港人壽保險 新產品 2026 | C9: 2026-05-31 08:00 HKT | D9: Yes | E9: Specified Traditional Chinese query.
A10: Search query | B10: 儲蓄保險 新推出 香港 2026 | C10: 2026-05-31 08:00 HKT | D10: Yes | E10: Specified Traditional Chinese query.
A11: Search query | B11: 危疾保險 新計劃 香港 2026 | C11: 2026-05-31 08:00 HKT | D11: Yes | E11: Specified Traditional Chinese query.
A12: Search query | B12: QDAP 合資格延期年金 新計劃 2026 | C12: 2026-05-31 08:00 HKT | D12: Limited | E12: Specified Traditional Chinese query; no new top-10 QDAP launch found.
... A27: Financial news | B27: https://www.caproasia.com/2026/05/25/hong-kong-chow-tai-fook-life-insurance-ctf-life-launches-bnp-paribas-linked-index-universal-life-product-for-professional-investors-shiny-treasure-indexed-universal-life-insurance-plan-featuring/ | C27: 2026-05-31 08:00 HKT | D27: Yes | E27: Non-target insurer market signal; not included in top-10 tracker rows.
